MANIFEST.in
README.md
setup.py
fitting/__init__.py
fitting/admin.py
fitting/forms.py
fitting/middleware.py
fitting/models.py
fitting/tests.py
fitting/urls.py
fitting/version.py
fitting/views.py
fitting.egg-info/PKG-INFO
fitting.egg-info/SOURCES.txt
fitting.egg-info/dependency_links.txt
fitting.egg-info/entry_points.txt
fitting.egg-info/requires.txt
fitting.egg-info/top_level.txt
fitting/management/__init__.py
fitting/management/commands/__init__.py
fitting/migrations/0001_initial.py
fitting/migrations/__init__.py
fitting/south_migrations/0001_initial.py
fitting/south_migrations/0002_auto__add_fitting__add_unique_fitting_fitting_type_source_id_source_ty.py
fitting/south_migrations/__init__.py
fitting/templates/fitting/.keep
fitting/templates/fitting/index.html
fitting/templatetags/__init__.py