Metadata-Version: 1.1
Name: fitting
Version: 1.0.6
Summary: fitting
Home-page: http://www.github.com/mcfletch/fitting
Author: VRPlumber Consulting Inc.
Author-email: mcfletch@vrplumber.com
License: MIT
Keywords: django
Platform: UNKNOWN
Classifier: Programming Language :: Python
Classifier: Framework :: Django
Classifier: Topic :: Internet :: WWW/HTTP
Classifier: Topic :: Internet :: WWW/HTTP :: WSGI :: Application
